selene/__init__.py
selene/browser.py
selene/browsers.py
selene/bys.py
selene/conditions.py
selene/config.py
selene/driver.py
selene/elements.py
selene/environment.py
selene/exceptions.py
selene/factory.py
selene/helpers.py
selene/version.py
selene/wait.py
selene/abctypes/__init__.py
selene/abctypes/conditions.py
selene/abctypes/locators.py
selene/abctypes/search_context.py
selene/abctypes/webdriver.py
selene/abctypes/webelement.py
selene/api/__init__.py
selene/common/__init__.py
selene/common/delegation.py
selene/common/none_object.py
selene/support/__init__.py
selene/support/by.py
selene/support/jquery_style_selectors.py
selene/support/conditions/__init__.py
selene/support/conditions/be.py
selene/support/conditions/have.py
selene_kentastik-1.0.0a16.dist-info/LICENSE
selene_kentastik-1.0.0a16.dist-info/METADATA
selene_kentastik-1.0.0a16.dist-info/WHEEL
selene_kentastik-1.0.0a16.dist-info/top_level.txt
selene_kentastik-1.0.0a16.dist-info/RECORD
