Metadata-Version: 2.1
Name: selene-kentastik
Version: 1.0.0a16
Summary: Concise API for selenium in Python + Ajax support + PageObjects (Selenide port from Java to Python)
Home-page: http://github.com/kentastik/selene/
Author: kentastik
Author-email: e.a.samsonov@gmail.com
License: MIT
Download-URL: https://github.com/kentastik/selene/tarball/1.0.0a16
Keywords: testing,selenium==3.141.0,selenide,browser,pageobject,widget,wrapper
Platform: any
Classifier: Programming Language :: Python
Classifier: Programming Language :: Python :: 2
Classifier: Programming Language :: Python :: 3
Classifier: Development Status :: 3 - Alpha
Classifier: Natural Language :: English
Classifier: Environment :: Web Environment
Classifier: Intended Audience :: Developers
Classifier: License :: OSI Approved :: Apache Software License
Classifier: Operating System :: OS Independent
Classifier: Topic :: Software Development :: Libraries :: Python Modules
Classifier: Topic :: Software Development :: Libraries :: Application Frameworks
Classifier: Topic :: Internet :: WWW/HTTP :: Browsers
Classifier: Topic :: Software Development :: Testing
Requires-Dist: selenium
Requires-Dist: webdriver-manager
Requires-Dist: future
Requires-Dist: backports.functools-lru-cache
Requires-Dist: six
